convappro/__init__.py
convappro/code.py
convappro-0.0.2.dist-info/LICENSE
convappro-0.0.2.dist-info/METADATA
convappro-0.0.2.dist-info/WHEEL
convappro-0.0.2.dist-info/top_level.txt
convappro-0.0.2.dist-info/RECORD
