Metadata-Version: 2.1
Name: convappro
Version: 0.0.2
Summary: Projet d'analyse: Sujet 31
Home-page: https://github.com/henrimacedo/convappro.git
Author: Marion NOVERRAZ, Mostafa HAGHVIRDILOO, Alexandre RAMDOO, Henri MACEDO GONCALVES
Author-email: henri.macedo-goncalves@etu.unistra.fr
License: UNKNOWN
Project-URL: Bug Tracker, https://github.com/henrimacedo/convappro.git/issues
Platform: UNKNOWN
Classifier: Programming Language :: Python :: 3
Classifier: License :: OSI Approved :: MIT License
Classifier: Operating System :: OS Independent
Requires-Python: >=3.0
License-File: LICENSE
